<?xml version="1.0"?><Language><lng val="Paramètres de la base de données" id="lang_da_DatabaseSettings" prop="innerHTML" /><lng val="Modifier les détails de connexion de la base de données ici" id="lang_da_AddMod_DCDH" prop="innerHTML" /><lng val="Indicateur par défaut" id="langDefaultIndicator" prop="innerHTML" /><lng val="Sélectionné" id="langSelected" prop="innerHTML" /><lng val="Sélectionné" id="langSelected_da" prop="innerHTML" /><lng val="Sélectionnez la rubrique" id="langSelectTopic" prop="innerHTML" /><lng val="Ok" id="indOk" prop="value" /><lng val="Annuler" id="indCancel" prop="value" /><lng val="Sélectionner une zone" id="langSelectArea" prop="innerHTML" /><lng val="Ok" id="areaOk" prop="value" /><lng val="Annuler" id="areaCancel" prop="value" /><lng val="Définir la zone par défaut" id="langSetDefaultArea" prop="innerHTML" /><lng val="Enregistrer" id="langSave" prop="value" /><lng val="Précédent" id="btnlang_da_Back" prop="value" /><lng val="Terminer" id="btnlangFinish" prop="value" /><lng val="Tout sélectionner" id="langHiddenSelectAll" prop="value" /><lng val="Choisissez le niveau de la zone" id="langHiddenSelectarealevel" prop="value" /><lng val="Par arborescence" id="langHiddenByTree" prop="value" /><lng val="Liste par ordre alphabétique" id="langHiddenListAtoZ" prop="value" /><lng val="Liste par ordre alphabétique" id="langHiddenAlphabetically" prop="value" /><lng val="Par carte" id="langHiddenByMap" prop="value" /><lng val="Rechercher" id="langHiddenSearch" prop="value" /><lng val="Voir les sélections" id="langHiddenViewselections" prop="value" /><lng val="Métadonnées" id="langHiddenMetadata" prop="value" /><lng val="Afficher là où  existent des données" id="langHiddenShowwheredataexist" prop="value" /><lng val="Effacer" id="langHiddenClear" prop="value" /><lng val="Fermer" id="langHiddenClose" prop="value" /><lng val="Premier" id="langHiddenFirst" prop="value" /><lng val="Précédent" id="langHiddenBack" prop="value" /><lng val="Suivant" id="langHiddenNext" prop="value" /><lng val="Dernier" id="langHiddenLast" prop="value" /><lng val="Page" id="langHiddenPage" prop="value" /><lng val="Arborescence" id="langHiddenTree" prop="value" /><lng val="Liste par ordre alphabétique" id="langHiddenAtoZ" prop="value" /><lng val="Secteur" id="langHiddenSector" prop="value" /><lng val="Objectif" id="langHiddenGoal" prop="value" /><lng val="Source" id="langHiddenSource" prop="value" /><lng val="Institution" id="langHiddenInstitution" prop="value" /><lng val="Thème" id="langHiddenTheme" prop="value" /><lng val="Convention" id="langHiddenConvention" prop="value" /><lng val="Cadre conceptuel" id="langHiddenConceptualFramework" prop="value" /><lng val="Sélectionner sous-groupe" id="langHiddenselectsubgroup" prop="value" /><lng val="Ok" id="langHiddenOK" prop="value" /><lng val="Dimensions des sous-groupes" id="langHiddenSubgroupDimensions" prop="value" /><lng val="Plus" id="langHiddenMore" prop="value" /><lng val="Générer un plan du site" id="Btn_GenerateSiteMap" prop="value" /></Language>