<?xml version="1.0"?><Language><lng val="Hide Column" id="langHideColumn" prop="innerHTML" /><lng val="Area" id="langArea" prop="value" /><lng val="Topic" id="langTopic" prop="value" /><lng val="Time Period " id="langTimePeriod" prop="innerHTML" /><lng val="Most Recent" id="langMostRecent" prop="innerHTML" /><lng val="Source" id="langSource" prop="innerHTML" /><lng val="Data Filter" id="langDataFilter" prop="innerHTML" /><lng val="Sort Order" id="langSortOrder" prop="innerHTML" /><lng val="Data Filter" id="langDataFilterHead" prop="innerHTML" /><lng val="From " id="langFrom" prop="innerHTML" /><lng val="To" id="langTo" prop="innerHTML" /><lng val="Table" id="langTable" prop="innerHTML" /><lng val="Line" id="langLine" prop="innerHTML" /><lng val="Column" id="langColumn" prop="innerHTML" /><lng val="Bar" id="langBar" prop="innerHTML" /><lng val="Area" id="langAreaBar" prop="innerHTML" /><lng val="Pie" id="langPie" prop="innerHTML" /><lng val="Radar" id="langRadar" prop="innerHTML" /><lng val="Map" id="langMap" prop="innerHTML" /><lng val="Scatter" id="langScatter" prop="innerHTML" /><lng val="Pyramid" id="langPyramid" prop="innerHTML" /><lng val="Treemap" id="langTreemap" prop="innerHTML" /><lng val="Cloud" id="langCloud" prop="innerHTML" /><lng val="both" id="langHiddenBoth" prop="value" /><lng val="Tree" id="langHiddenTree" prop="value" /><lng val="List Alphabetically" id="langHiddenAtoZ" prop="value" /><lng val="List Alphabetically" id="langHiddenListAtoZ" prop="value" /><lng val="List Alphabetically" id="langHiddenAlphabetically" prop="value" /><lng val="Search" id="langHiddenSearch" prop="value" /><lng val="View selections" id="langHiddenViewselections" prop="value" /><lng val="Sector" id="langHiddenSector" prop="value" /><lng val="Goal" id="langHiddenGoal" prop="value" /><lng val="Source" id="langHiddenSource" prop="value" /><lng val="Institution" id="langHiddenInstitution" prop="value" /><lng val="Theme" id="langHiddenTheme" prop="value" /><lng val="Convention" id="langHiddenConvention" prop="value" /><lng val="select subgroup" id="langHiddenselectsubgroup" prop="value" /><lng val="Select all" id="langHiddenSelectAll" prop="value" /><lng val="Show where data exist" id="langHiddenShowwheredataexist" prop="value" /><lng val="OK" id="langHiddenOK" prop="value" /><lng val="Clear" id="langHiddenClear" prop="value" /><lng val="Close" id="langHiddenClose" prop="value" /><lng val="Subgroup Dimensions" id="langHiddenSubgroupDimensions" prop="value" /><lng val="More" id="langHiddenMore" prop="value" /><lng val="Metadata" id="langHiddenMetadata" prop="value" /><lng val="Select Topic" id="langSelectTopic" prop="innerHTML" /><lng val="OK" id="indOk" prop="value" /><lng val="Cancel" id="indCancel" prop="value" /><lng val="Data" id="aDS" prop="innerHTML" /><lng val="Gallery" id="aGalleries" prop="innerHTML" /><lng val="News" id="aNews" prop="innerHTML" /><lng val="My Data" id="aMydata" prop="innerHTML" /><lng val="Catalog" id="aCatalog" prop="innerHTML" /><lng val="Loading Data..." id="divShowLoadingText" prop="innerHTML" /><lng val="Callout text" id="divCalloutText" prop="innerHTML" /><lng val="Download as PNG" id="lang_Download_PNG" prop="innerHTML" /><lng val="Download as SVG" id="lang_Download_SVG" prop="innerHTML" /><lng val="Download as XLS" id="lang_Download_XLS" prop="innerHTML" /><lng val="Download as XLS" id="lang_tbl_Download_XLS" prop="innerHTML" /><lng val="Download as Image" id="lang_Download_Image" prop="innerHTML" /><lng val="Download as XLS" id="lang_map_Download_XLS" prop="innerHTML" /><lng val="Download as KML" id="lang_Download_KML" prop="innerHTML" /><lng val="Visualization" id="lang_Visualization" prop="innerHTML" /><lng val="Settings" id="lang_Settings" prop="innerHTML" /><lng val="Table" id="lang_Table" prop="innerHTML" /><lng val="Line" id="lang_Line" prop="innerHTML" /><lng val="Line" id="lang_Line_di" prop="innerHTML" /><lng val="Column" id="lang_Column" prop="innerHTML" /><lng val="Column" id="lang_Column_di" prop="innerHTML" /><lng val="Bar" id="lang_Bar" prop="innerHTML" /><lng val="Bar" id="lang_Bar_di" prop="innerHTML" /><lng val="Area" id="lang_Area" prop="innerHTML" /><lng val="Area" id="lang_Area_di" prop="innerHTML" /><lng val="Pie" id="lang_Pie" prop="innerHTML" /><lng val="Map" id="lang_Map" prop="innerHTML" /><lng val="Map" id="lang_Map_di" prop="innerHTML" /><lng val="Pyramid" id="lang_Pyramid" prop="innerHTML" /><lng val="Treemap" id="lang_Treemap" prop="innerHTML" /><lng val="Radar" id="lang_Radar" prop="innerHTML" /><lng val="Show Border" id="langVcShowBdr" prop="innerHTML" /><lng val="Gridlines [X-Axis]" id="langVcGridLnX" prop="innerHTML" /><lng val="Gridlines [Y-Axis]" id="langVcGridLnY" prop="innerHTML" /><lng val="Label" id="langVcDataLbl" prop="innerHTML" /><lng val="Legend" id="langVcLegend" prop="innerHTML" /><lng val="General" id="lang_General" prop="innerHTML" /><lng val="X-Pos." id="lang_XPos" prop="innerHTML" /><lng val="Y-Pos." id="lang_YPos" prop="innerHTML" /><lng val="Show" id="lang_Show" prop="innerHTML" /><lng val="Decimals" id="lang_Decimals" prop="innerHTML" /><lng val="Use 1,000 separator" id="lang_U_1000separator" prop="innerHTML" /><lng val="Titles/Labels" id="lang_Titles_Labels" prop="innerHTML" /><lng val="Series" id="lang_Series" prop="innerHTML" /><lng val="Label" id="lang_Data_Labels" prop="innerHTML" /><lng val="Borders" id="lang_Borders" prop="innerHTML" /><lng val="North symbol" id="lang_North_symbol" prop="innerHTML" /><lng val="Scale" id="lang_Scale" prop="innerHTML" /><lng val="General" id="lang_map_General" prop="innerHTML" /><lng val="Title" id="lang_Title" prop="innerHTML" /><lng val="Label Row 1" id="lang_Data_Label" prop="innerHTML" /><lng val="Legend Title" id="lang_Legend_Title" prop="innerHTML" /><lng val="Legend Body" id="lang_Legend_Body" prop="innerHTML" /><lng val="Disclaimer" id="lang_Disclaimer" prop="innerHTML" /><lng val="Titles/Labels" id="lang_map_Titles_Labels" prop="innerHTML" /><lng val="Theme" id="mapTxtSelTheme" prop="innerHTML" /><lng val="Select Series" id="mapTxtSelSeries" prop="innerHTML" /><lng val="Show Theme" id="mapTxtShowTh" prop="innerHTML" /><lng val="Break Type" id="lang_Break_Type" prop="innerHTML" /><lng val="Equal Count" id="lang_Equal_Count" prop="innerHTML" /><lng val="Equal Size" id="lang_Equal_Size" prop="innerHTML" /><lng val="Continuous" id="lang_Continuous" prop="innerHTML" /><lng val="Discontinuous" id="lang_Discontinuous" prop="innerHTML" /><lng val="Break Count" id="lang_Break_Count" prop="innerHTML" /><lng val="Width" id="lang_Width" prop="innerHTML" /><lng val="Height" id="lang_Height" prop="innerHTML" /><lng val="Marker Style" id="lang_Marker_Style" prop="innerHTML" /><lng val="Marker Size" id="lang_Marker_Size" prop="innerHTML" /><lng val="Marker Color" id="lang_Marker_Color" prop="innerHTML" /><lng val="Marker Value" id="lang_Marker_Value" prop="innerHTML" /><lng val="Theme" id="lang_Theme" prop="innerHTML" /><lng val="Pivoting" id="lang_Pivoting" prop="innerHTML" /><lng val="Select Area" id="lang_Select_Area" prop="innerHTML" /><lng val="OK" id="areaOk" prop="value" /><lng val="Cancel" id="areaCancel" prop="value" /><lng val="Show keywords here" id="tab-ksection" prop="innerHTML" /><lng val="Visualization" id="tab-v" prop="innerHTML" /><lng val="Data" id="tab-d" prop="innerHTML" /><lng val="Source" id="tab-s" prop="innerHTML" /><lng val="Keywords" id="tab-k" prop="innerHTML" /><lng val="General" id="lang_Map_General" prop="innerHTML" /><lng val="Modify your settings here" id="lang_Modify_YSH" prop="innerHTML" /><lng val="OK" id="lang_ppup_OK" prop="value" /><lng val="Cancel" id="lang_ppup_Cancel" prop="value" /><lng val="Apply" id="lang_ppup_Apply" prop="value" /><lng val="Symbol" id="lang_Symbol" prop="innerHTML" /><lng val="Modify your settings here" id="lang_Map_Modify_YSH" prop="innerHTML" /><lng val="Marker Font" id="lang_Marker_Font" prop="innerHTML" /><lng val="Color" id="lang_Color" prop="innerHTML" /><lng val="Size" id="lang_Size" prop="innerHTML" /><lng val="Opacity" id="lang_Opacity" prop="innerHTML" /><lng val="Webdings" id="lang_Webdings" prop="innerHTML" /><lng val="Wingdings" id="lang_Wingdings" prop="innerHTML" /><lng val="OK" id="lang_Map_OK" prop="value" /><lng val="Cancel" id="lang_Map_Cancel" prop="value" /><lng val="Image Settings" id="lang_Image_Settings" prop="innerHTML" /><lng val="Modify your settings here" id="lang_Map_ppup_Modify_YSH" prop="innerHTML" /><lng val="Show Legend" id="lang_Show_Legend" prop="innerHTML" /><lng val="Width" id="lang_ppup_Width" prop="innerHTML" /><lng val="Height" id="lang_ppup_Heigth" prop="innerHTML" /><lng val="Image Format" id="lang_ppup_Image_Format" prop="innerHTML" /><lng val="PNG" id="lang_PNG" prop="innerHTML" /><lng val="JPG" id="lang_JPG" prop="innerHTML" /><lng val="GIF" id="lang_GIF" prop="innerHTML" /><lng val="OK" id="lang_ppup_Map_OK" prop="value" /><lng val="Cancel" id="lang_ppup_Map_Cancel" prop="value" /><lng val="Gallery" id="lang_ppup_Gallery" prop="value" /><lng val="Save Presentation" id="lang_ppup_SavePres" prop="value" /><lng val="Enter inputs to save presentation into gallery" id="lang_ppup_SavePresDesc" prop="value" /><lng val="Name" id="lang_ppup_Name" prop="value" /><lng val="Keywords" id="lang_ppup_Keywords" prop="value" /><lng val="Description" id="lang_ppup_Desc" prop="value" /><lng val="OK" id="lang_ppup_OkEle" prop="value" /><lng val="Cancel" id="lang_ppup_CancelEle" prop="value" /><lng val="Apply" id="btnApply" prop="value" /><lng val="Area" id="langAreaText" prop="value" /><lng val="Indicator" id="langIndicatorText" prop="value" /><lng val="Scatter" id="lang_Scatter_di" prop="innerHTML" /><lng val="Time Period " id="langTimePeriodText" prop="value" /><lng val="Arrange" id="langArrange" prop="innerHTML" /><lng val="Pivot" id="langPivot" prop="innerHTML" /><lng val="Swap" id="langSwap" prop="innerHTML" /><lng val="Go to parent" id="lngGoToParent" prop="value" /><lng val="General" id="lngMapPopGeneral" prop="innerHTML" /><lng val="Modify your settings here" id="lngMapPopModifySetting" prop="innerHTML" /><lng val="Label" id="lngMapPopLabel" prop="innerHTML" /><lng val="Border" id="lngMapPopBorder" prop="innerHTML" /><lng val="Layer" id="lngMapPopLayer" prop="innerHTML" /><lng val="Label On" id="lngMapPopLblOn" prop="innerHTML" /><lng val="Area Id" id="lngMapPopAreaid" prop="innerHTML" /><lng val="Area Name" id="lngMapPopAreaNm" prop="innerHTML" /><lng val="Data Value" id="lngMapPopDataValue" prop="innerHTML" /><lng val="Time Period " id="lngMapPopTmPeriod" prop="innerHTML" /><lng val="Multi-row" id="lngMapPopMultiRow" prop="innerHTML" /><lng val="Indented" id="lngMapPopIndented" prop="innerHTML" /><lng val="Show where data exists" id="lngMapPopSwde" prop="innerHTML" /><lng val="Effects" id="lngMapPopEffects" prop="innerHTML" /><lng val="Effect Type" id="lngMapPopEffectTp" prop="innerHTML" /><lng val="Depth" id="lngMapPopDepth" prop="innerHTML" /><lng val="Shadow" id="lngMapPopShadow" prop="innerHTML" /><lng val="Embossed" id="lngMapPopEmbossed" prop="innerHTML" /><lng val="Block" id="lngMapPopBlock" prop="innerHTML" /><lng val="Gradient" id="lngMapPopGradient" prop="innerHTML" /><lng val="Reflect" id="lngMapPopReflect" prop="innerHTML" /><lng val="Show Border" id="lngMapPopShowBorder" prop="innerHTML" /><lng val="Width" id="lngMapPopWidth" prop="innerHTML" /><lng val="Color" id="lngMapPopColor" prop="innerHTML" /><lng val="Style" id="lngMapPopStyle" prop="innerHTML" /><lng val="Base" id="lngMapPopTBase" prop="innerHTML" /><lng val="Feature" id="lngMapPopTFeature" prop="innerHTML" /><lng val="First" id="lngMapPopIcnFirst" prop="innerHTML" /><lng val="Last" id="lngMapPopIcnLast" prop="innerHTML" /><lng val="Up" id="lngMapPopIcnUp" prop="innerHTML" /><lng val="Down" id="lngMapPopIcnDown" prop="innerHTML" /><lng val="Disputed Boundries" id="lngMapPopDisputedBdr" prop="innerHTML" /><lng val="Themes" id="lngMapPopThemes" prop="innerHTML" /><lng val="Theme" id="lngMapPopTheme" prop="innerHTML" /><lng val="Legend" id="lngMapPopLegend" prop="innerHTML" /><lng val="Chart Settings" id="lngMapPopChartSetting" prop="innerHTML" /><lng val="Theme Name" id="lngMapPopThemeName" prop="innerHTML" /><lng val="Theme Type" id="lngMapPopThemeType" prop="innerHTML" /><lng val="Series" id="lngMapPopThemeSeries" prop="innerHTML" /><lng val="Chart Type" id="lngMapPopThChatType" prop="innerHTML" /><lng val="Column" id="lngMapPopThChatColumn" prop="innerHTML" /><lng val="Pie" id="lngMapPopThChatPie" prop="innerHTML" /><lng val="Line" id="lngMapPopThChatLine" prop="innerHTML" /><lng val="Color" id="lngMapPopThColor" prop="innerHTML" /><lng val="Hatch" id="lngMapPopThHatch" prop="innerHTML" /><lng val="Dot Density" id="lngMapPopThDotden" prop="innerHTML" /><lng val="Chart" id="lngMapPopThChart" prop="innerHTML" /><lng val="Symbol" id="lngMapPopThSymbol" prop="innerHTML" /><lng val="Break Count" id="lngMapPopBrkCount" prop="innerHTML" /><lng val="Break Type" id="lngMapPopBrkType" prop="innerHTML" /><lng val="Equal Count" id="lngMapPopBrkEqCount" prop="innerHTML" /><lng val="Equal Size" id="lngMapPopBrkEqSize" prop="innerHTML" /><lng val="Continuous" id="lngMapPopBrkCont" prop="innerHTML" /><lng val="Discontinuous" id="lngMapPopBrkDiscont" prop="innerHTML" /><lng val="Min" id="lngMapPopLgMin" prop="innerHTML" /><lng val="Max" id="lngMapPopLgMax" prop="innerHTML" /><lng val="Decimals" id="lngMapPopLgDecimals" prop="innerHTML" /><lng val="Upload Settings" id="lngMapPopUploadSetting" prop="innerHTML" /><lng val="Smooth" id="lngMapPopLgSmooth" prop="innerHTML" /><lng val="Download Settings" id="lngMapPopDwnSetting" prop="innerHTML" /><lng val="Marker Style" id="lngMapPopMarStyle" prop="innerHTML" /><lng val="Marker Size" id="lngMapPopMarSize" prop="innerHTML" /><lng val="Marker Color" id="lngMapPopMarColor" prop="innerHTML" /><lng val="Marker Value" id="lngMapPopMarValue" prop="innerHTML" /><lng val="Opacity" id="lngMapPopMarOpacity" prop="innerHTML" /><lng val="View Data Value" id="lngMapPopCSViewDtVal" prop="innerHTML" /><lng val="Decimals" id="lngMapPopCSDecimals" prop="innerHTML" /><lng val="Width" id="lngMapPopCSWidth" prop="innerHTML" /><lng val="Height" id="lngMapPopCSHeight" prop="innerHTML" /><lng val="Time Series" id="lngMapPopCSTimeSeries" prop="innerHTML" /><lng val="Most Recent" id="lngMapPopCSMostRecent" prop="innerHTML" /><lng val="Select all" id="lngSelectall" prop="value" /><lng val="Clear all" id="lngClearall" prop="value" /><lng val="More" id="lngMore" prop="value" /><lng val="Sorting" id="lngSorting" prop="value" /><lng val="Hide Columns" id="lngHideCol" prop="value" /><lng val="Most recent data" id="lngMRD" prop="value" /><lng val="Gridlines" id="lngGridlineTxt" prop="innerHTML" /><lng val="Chart Area" id="lngChartAreaTxt" prop="innerHTML" /><lng val="Plot Area" id="lngPlotAreaTxt" prop="innerHTML" /><lng val="Radius" id="lngRadiusTxt" prop="innerHTML" /><lng val="Select Gridlines Axis" id="lngSelGLAxisTxt" prop="innerHTML" /><lng val="X-Axis" id="lngXAxisTxt" prop="innerHTML" /><lng val="Y-Axis" id="lngYAxisTxt" prop="innerHTML" /><lng val="Major Gridlines" id="lngMajorGLTxt" prop="innerHTML" /><lng val="Minor Gridlines" id="lngMinorGLTxt" prop="innerHTML" /><lng val="Background Color" id="lngBgColorTxt" prop="innerHTML" /><lng val="No Fill" id="lngNoFillTxt" prop="innerHTML" /><lng val="Solid Fill" id="lngSolidFillTxt" prop="innerHTML" /><lng val="Gradient Fill" id="lngGradientFillTxt" prop="innerHTML" /><lng val="Fill Color" id="lngFillColorTxt" prop="innerHTML" /><lng val="Color 1" id="lngColor1Txt" prop="innerHTML" /><lng val="Color 2" id="lngColor2Txt" prop="innerHTML" /><lng val="Show Legend" id="lngShowLegendTxt" prop="innerHTML" /><lng val="Border Width" id="lngBdrWidthTxt" prop="innerHTML" /><lng val="Border Color" id="lngBdrColorTxt" prop="innerHTML" /><lng val="Border Radius" id="lngBdrRadiusTxt" prop="innerHTML" /><lng val="Font Size" id="lngFontSizeTxt" prop="innerHTML" /><lng val="Position" id="lngPositionTxt" prop="innerHTML" /><lng val="Floating" id="lngFloatingTxt" prop="innerHTML" /><lng val="X-Pos." id="lngXPosTxt" prop="innerHTML" /><lng val="Y-Pos." id="lngYPosTxt" prop="innerHTML" /><lng val="Fixed" id="lngFixedTxt" prop="innerHTML" /><lng val="Legend Width" id="lngLengendWidthTxt" prop="innerHTML" /><lng val="Auto" id="lngAutoTxt" prop="innerHTML" /><lng val="Option" id="lngOptionTxt" prop="innerHTML" /><lng val="Series Type" id="lngSeriesTypeTxt" prop="innerHTML" /><lng val="Line" id="lngLineTxt" prop="innerHTML" /><lng val="Column" id="lngColumnTxt" prop="innerHTML" /><lng val="Radial Axis" id="lngRadialAxisTxt" prop="innerHTML" /><lng val="Horizontal" id="lngHorizontalTxt" prop="innerHTML" /><lng val="Vertical" id="lngVerticalTxt" prop="innerHTML" /><lng val="both" id="lngBothTxt" prop="innerHTML" /><lng val="None" id="lngNoneTxt" prop="innerHTML" /><lng val="Forms" id="lngFormsTxt" prop="innerHTML" /><lng val="Segment" id="lngSegmentTxt" prop="innerHTML" /><lng val="Curve" id="lngCurveTxt" prop="innerHTML" /><lng val="Chart Type" id="lngCharTypeTxt" prop="innerHTML" /><lng val="Circular" id="lngCircularTxt" prop="innerHTML" /><lng val="Polygonal" id="lngPolygonalTxt" prop="innerHTML" /><lng val="Left" id="lngLeftTxt" prop="innerHTML" /><lng val="Right" id="lngRightTxt" prop="innerHTML" /><lng val="Top" id="lngTopTxt" prop="innerHTML" /><lng val="Bottom" id="lngBottomTxt" prop="innerHTML" /><lng val="Series Option" id="lngSeriesOptionTxt" prop="innerHTML" /><lng val="Fill" id="lngFillTxt" prop="innerHTML" /><lng val="Overlap" id="lngOverlapTxt" prop="innerHTML" /><lng val="Gap" id="lngGapTxt" prop="innerHTML" /><lng val="Select Indicator" id="lngMapSingleThemeSelectIndTxt" prop="innerHTML" /><lng val="Select Series" id="lngMapSingleThemeSelectSrTxt" prop="innerHTML" /><lng val="Add Theme" id="lngMapAddTheme" prop="innerHTML" /><lng val="Select Style" id="lngSelectStyleTxt" prop="innerHTML" /><lng val="Solid" id="lngSolidTxt" prop="innerHTML" /><lng val="ShortDash" id="lngShortDashTxt" prop="innerHTML" /><lng val="ShortDot" id="lngShortDotTxt" prop="innerHTML" /><lng val="ShortDashDot" id="lngShortDashDotTxt" prop="innerHTML" /><lng val="ShortDashDotDot" id="lngShortDashDotDotTxt" prop="innerHTML" /><lng val="Dot" id="lngDotTxt" prop="innerHTML" /><lng val="Dash" id="lngDashTxt" prop="innerHTML" /><lng val="LongDash" id="lngLongDashTxt" prop="innerHTML" /><lng val="DashDot" id="lngDashDotTxt" prop="innerHTML" /><lng val="LongDashDot" id="lngLongDashDotTxt" prop="innerHTML" /><lng val="LongDashDotDot" id="lngLongDashDotDotTxt" prop="innerHTML" /><lng val="Left top" id="lngLeftTopTxt" prop="innerHTML" /><lng val="Left middle" id="lngLeftMiddleTxt" prop="innerHTML" /><lng val="Left bottom" id="lngLeftBottomTxt" prop="innerHTML" /><lng val="Right top" id="lngRightTopTxt" prop="innerHTML" /><lng val="Right middle" id="lngRightMiddleTxt" prop="innerHTML" /><lng val="Right bottom" id="lngRightBottomTxt" prop="innerHTML" /><lng val="Select" id="lngSelectTxt" prop="innerHTML" /><lng val="Top to bottom" id="lngTopToBottomTxt" prop="innerHTML" /><lng val="Bottom to top" id="lngBottomToTopTxt" prop="innerHTML" /><lng val="Left to right" id="lngLeftToRightTxt" prop="innerHTML" /><lng val="Right to left" id="lngRightToLeftTxt" prop="innerHTML" /><lng val="Chart" id="langVcBgChart" prop="innerHTML" /><lng val="Plot Area" id="langVcBgPArea" prop="innerHTML" /><lng val="Share" id="langShare" prop="innerHTML" /><lng val="Download" id="clickDownloadLabel" prop="innerHTML" /><lng val="Save As" id="langSaveAs" prop="innerHTML" /><lng val="Fill Color" id="cafillcolorpt" prop="innerHTML" /><lng val="Fill Color" id="pafillcolorpt" prop="innerHTML" /><lng val="Chart Title" id="lngChartTitleTxt" prop="innerHTML" /><lng val="Chart Subtitle" id="lngChartSubtitleTxt" prop="innerHTML" /><lng val="X Axis Title" id="lngXAxisTitleTxt" prop="innerHTML" /><lng val="X Axis Label" id="lngXAxisLabelTxt" prop="innerHTML" /><lng val="Y Axis Title" id="lngYAxisTitleTxt" prop="innerHTML" /><lng val="Y Axis Label" id="lngYAxisLabelTxt" prop="innerHTML" /><lng val="DataLabels" id="lngDataLabelsTxt" prop="innerHTML" /><lng val="Note" id="lngNoteTxt" prop="innerHTML" /><lng val="Source" id="lngSourceTxt" prop="innerHTML" /><lng val="Gridlines [X-Axis]" id="langGLTemp" prop="innerHTML" /><lng val="Name should not be blank" id="langNameMandatory" prop="innerHTML" /><lng val="&amp;lt;b&amp;gt;Not getting the line visualization you want? Make sure you've :&amp;lt;/b&amp;gt;&amp;lt;BR&amp;gt;&amp;lt;BR&amp;gt;&amp;lt;br /&amp;gt;&amp;lt;br /&amp;gt;&amp;lt;BR&amp;gt;&amp;lt;BR&amp;gt;&amp;lt;br /&amp;gt;&amp;lt;br /&amp;gt;Total count of data values less than 1000&amp;lt;BR&amp;gt;&amp;lt;BR&amp;gt;&amp;lt;br /&amp;gt;&amp;lt;br /&amp;gt;" id="lngLineChartHelpText" prop="value" /><lng val="Label Row 2" id="lang_Data_Label2" prop="innerHTML" /><lng val="Leader Line" id="lngMapPopLeaderLine" prop="innerHTML" /><lng val="Straight line" id="lngMapPopStraightLine" prop="innerHTML" /><lng val="Fields" id="lngMapPopFields" prop="innerHTML" /><lng val="Label Row 1" id="lngMapPopLblRow1" prop="innerHTML" /><lng val="Label Row 2" id="lngMapPopLblRow2" prop="innerHTML" /><lng val="General" id="lang_General_tab4" prop="innerHTML" /><lng val="Total Records " id="langDVTotalRecords" prop="value" /><lng val="Source " id="langDVSource" prop="value" /><lng val="Saving..." id="langSavingGallery" prop="value" /><lng val="Loading..." id="langLoadingGallery" prop="value" /><lng val="Loading Visualization..." id="langLoadingVisualization" prop="value" /><lng val="Loading Data..." id="langLoadingData" prop="value" /><lng val="Line" id="DVLine" prop="title" /><lng val="Stack line" id="DVStackLine" prop="title" /><lng val="Stack line 100%" id="DVStackLine100" prop="title" /><lng val="Column" id="DVColumn" prop="title" /><lng val="Stack column" id="DVStackColumn" prop="title" /><lng val="Stack column 100%" id="DVStackColumn100" prop="title" /><lng val="Bar" id="DVBar" prop="title" /><lng val="Stack bar" id="DVStackBar" prop="title" /><lng val="Stack bar 100%" id="DVStackBar100" prop="title" /><lng val="Area" id="DVArea" prop="title" /><lng val="Stack area" id="DVStackArea" prop="title" /><lng val="Stack area 100%" id="DVStackArea100" prop="title" /><lng val="Single theme" id="DVSingleTheme" prop="title" /><lng val="Multiple theme" id="DVMultipleTheme" prop="title" /><lng val="Google map 2D" id="DVGoogleMap2dTheme" prop="title" /><lng val="Google map 3D" id="DVGoogleMap3dTheme" prop="title" /><lng val="Default" id="mapNull" prop="title" /><lng val="Full Extent" id="mapFull" prop="title" /><lng val="Zoom in frame" id="mapZext" prop="title" /><lng val="Zoom In" id="mapZin" prop="title" /><lng val="Zoom Out" id="mapZout" prop="title" /><lng val="Pan" id="mapPan" prop="title" /><lng val="Nudge" id="mapNud" prop="title" /><lng val="Line chart is disabled when total number of data values are more than 1000" id="LineChartDisabled" prop="value" /><lng val="Column chart is disabled when total number of cells in data grid are greater than 2500" id="ColumnChartDisabled" prop="value" /><lng val="Bar chart is disabled when total number of cells in data grid are greater than 2500" id="BarChartDisabled" prop="value" /><lng val="Area chart is disabled when total number of cells in data grid are greater than 2500" id="AreaChartDisabled" prop="value" /><lng val="Pie chart is disabled when rows count in data grid is more than 100" id="PieChartDisabled" prop="value" /><lng val="Map is disabled when area information is not available." id="MapChartDisabled" prop="value" /><lng val="Pyramid is disabled when only one column is available or rows count is greater than 100, in data grid." id="PyramidChartDisabled" prop="value" /><lng val="Tree Map is disabled when there are more than 100 distinct values for first column of data grid." id="TreeMapChartDisabled" prop="value" /><lng val="Radar is disabled when data columns in grid are lesser than three." id="RadarChartDisabled" prop="value" /><lng val="2d Scatter is disabled when data columns are lesser than 2." id="ScatterChartDisabled" prop="value" /><lng val="Visualization is disabled." id="DefaultDisabled" prop="value" /><lng val="Please select" id="langPleaseSelect" prop="value" /><lng val="No data found for current selections" id="langNDFFCS" prop="value" /><lng val="Oops! Something is wrong with the selections. Please check the selections!" id="langSWWS" prop="value" /><lng val="Bold" id="ToolTipBold" prop="value" /><lng val="Italic" id="ToolTipItalic" prop="value" /><lng val="Underline" id="ToolTipUnderline" prop="value" /><lng val="Increase Font Size" id="ToolTipIncreaseFontSize" prop="value" /><lng val="Decrease Font Size" id="ToolTipDecreaseFontSize" prop="value" /><lng val="Font Color" id="ToolTipFontColor" prop="value" /><lng val="Fill Color" id="ToolTipFillColor" prop="value" /><lng val="Bars Border Color" id="ToolTipBarsBorderColor" prop="value" /><lng val="Bar's Border Line Width" id="ToolTipBarBorderLineWidth" prop="value" /><lng val="Dash Type" id="ToolTipDashType" prop="value" /><lng val="No Border Icon" id="ToolTipNoBorderIcon" prop="value" /><lng val="Fill Color1" id="ToolTipFillColor1" prop="value" /><lng val="Change Series Color" id="ToolTipChangeSeriesColor" prop="value" /><lng val="Change Theme Color" id="ToolTipChangeThemeColor" prop="value" /><lng val="45째 Text Direction" id="ToolTipCustomTextDirection45Text" prop="value" /><lng val="-45째 Text Direction" id="ToolTipCustomTextDirectionMinus45Text" prop="value" /><lng val="90째 Text Direction" id="ToolTipCustomTextDirection90Text" prop="value" /><lng val="-90째 Text Direction " id="ToolTipCustomTextDirectionMinus90Text" prop="value" /><lng val="Horizontal Text Direction" id="ToolTipCustomTextHorizontal" prop="value" /><lng val="Hide Setting Bar" id="ToolTipHideSettingBar" prop="value" /><lng val="Show Setting Bar" id="ToolTipShowSettingBar" prop="value" /><lng val="Hide Filter Panel" id="ToolTipHideFilterpanel" prop="value" /><lng val="Show Filter Panel" id="ToolTipShowFilterPanel" prop="value" /><lng val="Sort A to Z" id="ToolTipSortAtoZ" prop="value" /><lng val="Sort Z to A" id="ToolTipSortZtoA" prop="value" /><lng val="Expand General Setting" id="ToolTipExpandGeneralSetting" prop="value" /><lng val="Expand Format Setting " id="ToolTipExpandFormatSetting" prop="value" /><lng val="Expand Theme Setting" id="ToolTipExpandSeriesSetting" prop="value" /><lng val="Area Id" id="langDVAreaID" prop="value" /><lng val="Timeline Animator Enabled" id="timeLineChkBoxValue" prop="value" /><lng val="Enable Timeline Animator" id="disabledTimelineChkBoxTitle" prop="value" /><lng val="Disable Timeline Animator" id="enabledTimelineChkBoxTitle" prop="value" /><lng val="Play Timeline Animator" id="playAnimatorBtnTitle" prop="value" /><lng val="Stop Timeline Animator" id="stopAnimatorBtnTitle" prop="value" /></Language>